MANIFEST.in
NOTICE
README.rst
setup.cfg
setup.py
Trawl.egg-info/PKG-INFO
Trawl.egg-info/SOURCES.txt
Trawl.egg-info/dependency_links.txt
Trawl.egg-info/top_level.txt
bin/trawl
tests/001-task-tests.py
tests/002-deps-tests.py
tests/003-dep-cycle-tests.py
tests/004-build-task-tests.py
tests/005-namespace-tests.py
tests/006-rule-tests.py
tests/100-file-list-tests.py
tests/101-delayed-deps-tests.py
tests/t.py
trawl/__init__.py
trawl/application.py
trawl/chain.py
trawl/const.py
trawl/decorators.py
trawl/exceptions.py
trawl/filelist.py
trawl/filetask.py
trawl/multitask.py
trawl/path.py
trawl/task.py
trawl/taskmanager.py