Metadata-Version: 1.0
Name: Trawl
Version: 0.2.1
Summary: Python port of Ruby Rake
Home-page: http://packages.python.org/Trawl/
Author: Paul J. Davis
Author-email: paul.joseph.davis@gmail.com
License: MIT
Platform: UNKNOWN
Classifier: Development Status :: 4 - Beta
Classifier: Environment :: Console
Classifier: Intended Audience :: Developers
Classifier: License :: OSI Approved :: MIT License
Classifier: Operating System :: POSIX
Classifier: Programming Language :: Python
Classifier: Topic :: Software Development :: Build Tools
Classifier: Topic :: Software Development :: Libraries
